pi_spm/__init__.py
Python_piSPM-7.10.0.2.dist-info/LICENSE.txt
Python_piSPM-7.10.0.2.dist-info/METADATA
Python_piSPM-7.10.0.2.dist-info/WHEEL
Python_piSPM-7.10.0.2.dist-info/top_level.txt
Python_piSPM-7.10.0.2.dist-info/RECORD
