Metadata-Version: 2.1
Name: Python-piSPM
Version: 7.10.0.2
Summary: Python piSPM is a Python wrapper for Pickering Switch Path Manager.
Home-page: https://www.pickeringtest.com
Author: Pickering Interfaces
Author-email: Pickering Interfaces <support@pickeringtest.com>
License: Copyright (c) 2017-2024 Pickering Interfaces Ltd.
Project-URL: homepage, https://www.pickeringtest.com/
License-File: LICENSE.txt
Requires-Dist: future
